PyTkGui/__init__.py
PyTkGui/cli.py
PyTkGui/objects.py
PyTkGui/static.py
PyTkGui/utils.py
PyTkGui/assets/icon.png
PyTkGui/assets/template.zip
PyTkGui/core/__init__.py
PyTkGui/core/loader.py
PyTkGui/core/parser.py
PyTkGui/widgets/__init__.py
PyTkGui/widgets/_base.py
PyTkGui/widgets/application.py
PyTkGui/widgets/conds.py
PyTkGui/widgets/controls.py
PyTkGui/widgets/displays.py
PyTkGui/widgets/layouts.py
PyTkGui/widgets/routers.py
PyTkGui/widgets/table copy.py
PyTkGui/widgets/table.py
PyTkGui-2021.7.2.dist-info/AUTHORS.md
PyTkGui-2021.7.2.dist-info/LICENSE
PyTkGui-2021.7.2.dist-info/METADATA
PyTkGui-2021.7.2.dist-info/WHEEL
PyTkGui-2021.7.2.dist-info/entry_points.txt
PyTkGui-2021.7.2.dist-info/top_level.txt
PyTkGui-2021.7.2.dist-info/RECORD
