Metadata-Version: 2.1
Name: PyTkGui
Version: 2021.7.2
Summary: python mvvm gui framework on tkinter
Home-page: https://github.com/eseunghwan/PyTkGui
Author: eseunghwan
Author-email: shlee0920@naver.com
License: MIT license
Keywords: tkinter python mvvm gui
Platform: UNKNOWN
Classifier: Development Status :: 2 - Pre-Alpha
Classifier: Intended Audience :: Developers
Classifier: License :: OSI Approved :: MIT License
Classifier: Programming Language :: Python :: 3
Classifier: Programming Language :: Python :: 3.7
Classifier: Programming Language :: Python :: 3.8
Requires-Python: >=3.7
License-File: LICENSE
License-File: AUTHORS.md
Requires-Dist: lxml
Requires-Dist: Pillow
